fastauth/__init__.py
fastauth/auth.py
fastauth/client.py
fastauth/decode.py
fastauth/env.py
fastauth/exceptions.py
fastauth/model.py
fastauth/request.py
teppen_fastauth-0.2.2.dist-info/LICENCE
teppen_fastauth-0.2.2.dist-info/METADATA
teppen_fastauth-0.2.2.dist-info/WHEEL
teppen_fastauth-0.2.2.dist-info/top_level.txt
teppen_fastauth-0.2.2.dist-info/RECORD
