Metadata-Version: 2.1
Name: teppen-fastauth
Version: 0.2.2
Summary: Authentication Library for FastAPI
Author: Yasufumi Kamiyama
License: MIT
License-File: LICENCE
Requires-Dist: fastapi
Requires-Dist: pydantic
Requires-Dist: PyJWT
Requires-Dist: cryptography
Requires-Dist: requests
